selenible/__init__.py
selenible/admin.py
selenible/cli.py
selenible/jupyter.py
selenible/version.py
selenible/drivers/__init__.py
selenible/drivers/android.py
selenible/drivers/base.py
selenible/drivers/chrome.py
selenible/drivers/dummy.py
selenible/drivers/edge.py
selenible/drivers/firefox.py
selenible/drivers/ie.py
selenible/drivers/opera.py
selenible/drivers/phantom.py
selenible/drivers/remote.py
selenible/drivers/safari.py
selenible/drivers/webkitgtk.py
selenible/modules/browser.py
selenible/modules/content.py
selenible/modules/ctrl.py
selenible/modules/imageproc.py
selenible/modules/screencast.py
selenible/modules/webhook.py
selenible/schema/base.yaml
selenible/seleniblepiter/kernel.json
selenible-0.0.4.dist-info/LICENSE
selenible-0.0.4.dist-info/METADATA
selenible-0.0.4.dist-info/WHEEL
selenible-0.0.4.dist-info/entry_points.txt
selenible-0.0.4.dist-info/top_level.txt
selenible-0.0.4.dist-info/RECORD
