Metadata-Version: 2.1
Name: selenible
Version: 0.0.4
Summary: selenium like ansible
Home-page: https://github.com/wtnb75/selenible
Author: Takashi WATANABE
Author-email: wtnb75@gmail.com
License: MIT
Keywords: selenium web test
Platform: UNKNOWN
Classifier: Development Status :: 3 - Alpha
Classifier: Intended Audience :: Developers
Classifier: License :: OSI Approved :: MIT License
Classifier: Topic :: Software Development :: Testing
Classifier: Programming Language :: Python :: 3
Requires-Python: >=3
Requires-Dist: selenium
Requires-Dist: click
Requires-Dist: PyYAML
Requires-Dist: jinja2
Requires-Dist: texttable
Requires-Dist: jsonpath-rw
Requires-Dist: toml
Requires-Dist: pillow
Requires-Dist: jsonschema
Requires-Dist: lxml
Requires-Dist: requests
